drb_impl_tar/__init__.py
drb_impl_tar/_version.py
drb_impl_tar/base_tar_node.py
drb_impl_tar/cortex.yml
drb_impl_tar/execptions.py
drb_impl_tar/tar_node.py
drb_impl_tar-1.0.2.data/data/requirements.txt
drb_impl_tar-1.0.2.dist-info/METADATA
drb_impl_tar-1.0.2.dist-info/WHEEL
drb_impl_tar-1.0.2.dist-info/entry_points.txt
drb_impl_tar-1.0.2.dist-info/top_level.txt
drb_impl_tar-1.0.2.dist-info/RECORD
