Metadata-Version: 2.1
Name: drb-impl-tar
Version: 1.0.2
Summary: DRB Tar implementation
Home-page: https://gitlab.com/drb-python/impl/tar
Author: GAEL Systems
Author-email: drb-python@gael.fr
License: UNKNOWN
Project-URL: Documentation, https://drb-python.gitlab.io/impl/tar
Project-URL: Source, https://gitlab.com/drb-python/impl/tar
Platform: UNKNOWN
Classifier: Programming Language :: Python :: 3.8
Classifier: License :: OSI Approved :: Apache Software License
Classifier: Operating System :: OS Independent
Requires-Python: >=3.8
Requires-Dist: drb (<1.1.0,>=1.0.1)
Requires-Dist: drb-impl-file (<1.1.0,>=1.0.0)
Requires-Dist: versioneer (>=0.20)
